{
  "kind": "collectionType",
  "collectionName": "restaurantes",
  "info": {
    "singularName": "restaurante",
    "pluralName": "restaurantes",
    "displayName": "Restaurante"
  },
  "options": {
    "draftAndPublish": true
  },
  "pluginOptions": {},
  "attributes": {
    "Nome": {
      "type": "string",
      "required": true,
      "unique": true
    },
    "Descricao": {
      "type": "blocks"
    },
    "categorias": {
      "type": "relation",
      "relation": "manyToMany",
      "target": "api::categoria.categoria",
      "mappedBy": "restaurantes"
    }
  }
}
